pany/__init__.py
pany/client.py
pany/config.py
pany/main.py
pany/models.py
pany/services/__init__.py
pany/services/database.py
pany/services/embedding.py
pany/services/file_processor.py
pany-0.1.0.dist-info/licenses/LICENSE
pany-0.1.0.dist-info/METADATA
pany-0.1.0.dist-info/WHEEL
pany-0.1.0.dist-info/entry_points.txt
pany-0.1.0.dist-info/top_level.txt
pany-0.1.0.dist-info/RECORD
