Metadata-Version: 2.4
Name: pany
Version: 0.1.0
Summary: PostgreSQL-native semantic search engine with multi-modal support (Beta)
Home-page: https://github.com/your-org/pany
Author: Pany Team
Author-email: Pany Team <hello@pany.ai>
Maintainer-email: Pany Team <hello@pany.ai>
License: MIT
Project-URL: Homepage, https://github.com/your-org/pany
Project-URL: Documentation, https://github.com/your-org/pany/blob/main/README.md
Project-URL: Repository, https://github.com/your-org/pany
Project-URL: Bug Tracker, https://github.com/your-org/pany/issues
Keywords: semantic-search,vector-database,postgresql,embedding,similarity-search,multimodal,rag
Classifier: Development Status :: 3 - Alpha
Classifier: Intended Audience :: Developers
Classifier: License :: OSI Approved :: MIT License
Classifier: Operating System :: OS Independent
Classifier: Programming Language :: Python :: 3
Classifier: Programming Language :: Python :: 3.9
Classifier: Programming Language :: Python :: 3.10
Classifier: Programming Language :: Python :: 3.11
Classifier: Programming Language :: Python :: 3.12
Classifier: Topic :: Database
Classifier: Topic :: Scientific/Engineering :: Artificial Intelligence
Classifier: Topic :: Software Development :: Libraries :: Python Modules
Classifier: Framework :: FastAPI
Requires-Python: >=3.9
License-File: LICENSE
Requires-Dist: fastapi>=0.100.0
Requires-Dist: uvicorn[standard]>=0.23.0
Requires-Dist: sqlalchemy>=2.0.0
Requires-Dist: psycopg2-binary>=2.9.0
Requires-Dist: sentence-transformers>=2.2.0
Requires-Dist: pillow>=10.0.0
Requires-Dist: numpy>=1.24.0
Requires-Dist: aiofiles>=23.0.0
Requires-Dist: python-multipart>=0.0.6
Requires-Dist: pdfplumber>=0.9.0
Requires-Dist: pandas>=2.0.0
Requires-Dist: python-magic>=0.4.27
Requires-Dist: plotly>=5.17.0
Requires-Dist: langchain>=0.1.0
Requires-Dist: langchain-openai>=0.0.8
Requires-Dist: pydantic>=2.0.0
Provides-Extra: dev
Requires-Dist: pytest>=7.0.0; extra == "dev"
Requires-Dist: black>=22.0.0; extra == "dev"
Requires-Dist: flake8>=4.0.0; extra == "dev"
Requires-Dist: mypy>=0.950; extra == "dev"
Requires-Dist: pre-commit>=2.20.0; extra == "dev"
Provides-Extra: api
Requires-Dist: fastapi>=0.100.0; extra == "api"
Requires-Dist: uvicorn[standard]>=0.23.0; extra == "api"
Dynamic: author
Dynamic: home-page
Dynamic: license-file
Dynamic: requires-python
